voyageai/__init__.py
voyageai/_base.py
voyageai/api_resources/__init__.py
voyageai/api_resources/api_requestor.py
voyageai/api_resources/api_resource.py
voyageai/api_resources/embedding.py
voyageai/api_resources/multimodal_embedding.py
voyageai/api_resources/reranking.py
voyageai/api_resources/response.py
voyageai/client.py
voyageai/client_async.py
voyageai/embeddings_utils.py
voyageai/error.py
voyageai/object/__init__.py
voyageai/object/embeddings.py
voyageai/object/multimodal_embeddings.py
voyageai/object/reranking.py
voyageai/py.typed
voyageai/util.py
voyageai/version.py
voyageai-0.3.0.dist-info/LICENSE
voyageai-0.3.0.dist-info/METADATA
voyageai-0.3.0.dist-info/WHEEL
voyageai-0.3.0.dist-info/RECORD
