Metadata-Version: 2.1
Name: voyageai
Version: 0.3.0
Summary: 
Author: Yujie Qian
Author-email: yujieq@voyageai.com
Requires-Python: >=3.9,<3.13
Classifier: Programming Language :: Python :: 3
Classifier: Programming Language :: Python :: 3.9
Classifier: Programming Language :: Python :: 3.10
Classifier: Programming Language :: Python :: 3.11
Classifier: Programming Language :: Python :: 3.12
Requires-Dist: aiohttp
Requires-Dist: aiolimiter
Requires-Dist: oldest-supported-numpy
Requires-Dist: pillow
Requires-Dist: pydantic (>=1.10.8)
Requires-Dist: requests
Requires-Dist: tenacity
Requires-Dist: tokenizers (>=0.14.0)
